psychopy_monkeys/__init__.py
psychopy_monkeys/components/__init__.py
psychopy_monkeys/components/_base.py
psychopy_monkeys/components/enderMonkey/__init__.py
psychopy_monkeys/components/enderMonkey/classic/enderMonkey.png
psychopy_monkeys/components/enderMonkey/classic/enderMonkey@2x.png
psychopy_monkeys/components/enderMonkey/dark/enderMonkey.png
psychopy_monkeys/components/enderMonkey/dark/enderMonkey@2x.png
psychopy_monkeys/components/enderMonkey/light/enderMonkey.png
psychopy_monkeys/components/enderMonkey/light/enderMonkey@2x.png
psychopy_monkeys/components/keyboardMonkey/__init__.py
psychopy_monkeys/components/keyboardMonkey/classic/keyboardMonkey.png
psychopy_monkeys/components/keyboardMonkey/classic/keyboardMonkey@2x.png
psychopy_monkeys/components/keyboardMonkey/dark/keyboardMonkey.png
psychopy_monkeys/components/keyboardMonkey/dark/keyboardMonkey@2x.png
psychopy_monkeys/components/keyboardMonkey/light/keyboardMonkey.png
psychopy_monkeys/components/keyboardMonkey/light/keyboardMonkey@2x.png
psychopy_monkeys/components/mouseMonkey/__init__.py
psychopy_monkeys/components/mouseMonkey/classic/mouseMonkey.png
psychopy_monkeys/components/mouseMonkey/classic/mouseMonkey@2x.png
psychopy_monkeys/components/mouseMonkey/dark/mouseMonkey.png
psychopy_monkeys/components/mouseMonkey/dark/mouseMonkey@2x.png
psychopy_monkeys/components/mouseMonkey/light/mouseMonkey.png
psychopy_monkeys/components/mouseMonkey/light/mouseMonkey@2x.png
psychopy_monkeys/components/sliderMonkey/__init__.py
psychopy_monkeys/components/sliderMonkey/classic/sliderMonkey.png
psychopy_monkeys/components/sliderMonkey/classic/sliderMonkey@2x.png
psychopy_monkeys/components/sliderMonkey/dark/sliderMonkey.png
psychopy_monkeys/components/sliderMonkey/dark/sliderMonkey@2x.png
psychopy_monkeys/components/sliderMonkey/light/sliderMonkey.png
psychopy_monkeys/components/sliderMonkey/light/sliderMonkey@2x.png
psychopy_monkeys/utils/__init__.py
psychopy_monkeys/utils/monkey.py
psychopy_monkeys-0.0.2.dist-info/METADATA
psychopy_monkeys-0.0.2.dist-info/WHEEL
psychopy_monkeys-0.0.2.dist-info/entry_points.txt
psychopy_monkeys-0.0.2.dist-info/top_level.txt
psychopy_monkeys-0.0.2.dist-info/RECORD
