Metadata-Version: 2.1
Name: psychopy-monkeys
Version: 0.0.2
Summary: Adds Components to PsychoPy which immitate participant input while in piloting mode.
Author-email: Todd Parsons <todd.e.parsons@gmail.com>
License: MIT
Project-URL: homepage, https://github.com/psychopy/psychopy-monkeys
Project-URL: changelog, https://github.com/psychopy/psychopy-monkeys/blob/main/CHANGELOG.md
Provides-Extra: docs
Requires-Dist: psychopy ; extra == 'docs'
Requires-Dist: sphinx ; extra == 'docs'
Requires-Dist: furo ; extra == 'docs'
Provides-Extra: tests
Requires-Dist: psychopy ; extra == 'tests'
Requires-Dist: pytest ; extra == 'tests'
